neutralocean/__init__.py
neutralocean/_vertsolve.py
neutralocean/bfs.py
neutralocean/data.py
neutralocean/fzero.py
neutralocean/label.py
neutralocean/lib.py
neutralocean/mixed_layer.py
neutralocean/ntp.py
neutralocean/stability.py
neutralocean/surface.py
neutralocean/traj.py
neutralocean/eos/__init__.py
neutralocean/eos/gsw.py
neutralocean/eos/gswc.py
neutralocean/eos/jmd95.py
neutralocean/eos/jmdfwg06.py
neutralocean/eos/polyTEOS10bsq.py
neutralocean/eos/tools.py
neutralocean/grid/__init__.py
neutralocean/grid/graph.py
neutralocean/grid/rectilinear.py
neutralocean/grid/tools.py
neutralocean/grid/tripolar.py
neutralocean/grid/xgcm.py
neutralocean/ppinterp/__init__.py
neutralocean/ppinterp/lib.py
neutralocean/ppinterp/linear.py
neutralocean/ppinterp/pchip.py
neutralocean/ppinterp/ppval.py
neutralocean/ppinterp/tools.py
neutralocean-2.4.1.dist-info/licenses/LICENSE.txt
tests/__init__.py
tests/test_eos.py
tests/test_fzero.py
tests/test_interp.py
tests/test_neutral_surfaces.py
neutralocean-2.4.1.dist-info/METADATA
neutralocean-2.4.1.dist-info/WHEEL
neutralocean-2.4.1.dist-info/top_level.txt
neutralocean-2.4.1.dist-info/RECORD
