Metadata-Version: 2.4
Name: neutralocean
Version: 2.4.1
Summary: Neutral Surfaces in the Ocean
Home-page: https://github.com/geoffstanley/neutralocean
Author: Geoff Stanley
Author-email: geoff.stanley@ec.gc.ca
License: MIT
Keywords: oceanography
Platform: any
Classifier: Development Status :: 4 - Beta
Classifier: Environment :: Console
Classifier: Intended Audience :: Science/Research
Classifier: Intended Audience :: Developers
Classifier: Intended Audience :: Education
Classifier: License :: OSI Approved :: MIT License
Classifier: Operating System :: OS Independent
Classifier: Programming Language :: Python
Classifier: Topic :: Scientific/Engineering
Classifier: Topic :: Education
Requires-Python: >=3.8
License-File: LICENSE.txt
Requires-Dist: numba
Requires-Dist: numpy
Requires-Dist: xarray
Requires-Dist: scipy
Requires-Dist: gsw
Requires-Dist: pooch
Requires-Dist: xgcm
Requires-Dist: netcdf4
Dynamic: license-file
